rki_covid_parser/__init__.py
rki_covid_parser/const.py
rki_covid_parser/parser.py
rki_covid_parser/model/__init__.py
rki_covid_parser/model/area.py
rki_covid_parser/model/country.py
rki_covid_parser/model/district.py
rki_covid_parser/model/state.py
rki_covid_parser-1.3.3.dist-info/LICENSE
rki_covid_parser-1.3.3.dist-info/METADATA
rki_covid_parser-1.3.3.dist-info/WHEEL
rki_covid_parser-1.3.3.dist-info/top_level.txt
rki_covid_parser-1.3.3.dist-info/RECORD
