Metadata-Version: 2.1
Name: rki-covid-parser
Version: 1.3.3
Summary: A simple rki covid numbers parser
Home-page: https://github.com/thebino/rki-covid-parser
Author: Stürmer, Benjamin
Author-email: webmaster@stuermer-benjamin.de
License: Apache Software License
Project-URL: Bug Tracker, https://github.com/thebino/rki-covid-parser/issues
Project-URL: Changelog, https://github.com/thebino/rki-covid-parser/blob/master/CHANGELOG.md
Keywords: covid,rki
Platform: UNKNOWN
Classifier: License :: OSI Approved :: Apache Software License
Classifier: Development Status :: 5 - Production/Stable
Classifier: Intended Audience :: Developers
Classifier: Intended Audience :: Science/Research
Classifier: Programming Language :: Python :: 3
Classifier: Operating System :: OS Independent
Classifier: Typing :: Typed
Requires-Python: !=2.*,>=3.6
License-File: LICENSE
Requires-Dist: aiohttp (>=3.5.2)
Provides-Extra: all
Requires-Dist: pytest (>=6.2.2) ; extra == 'all'
Requires-Dist: pytest-asyncio ; extra == 'all'
Requires-Dist: pytest-aiohttp ; extra == 'all'
Requires-Dist: pytest-cov ; extra == 'all'
Provides-Extra: test
Requires-Dist: pytest (>=6.2.2) ; extra == 'test'
Requires-Dist: pytest-asyncio ; extra == 'test'
Requires-Dist: pytest-aiohttp ; extra == 'test'
Requires-Dist: pytest-cov ; extra == 'test'
